{
  "kind": "singleType",
  "collectionName": "hologramm_praesentations",
  "info": {
    "singularName": "hologramm-praesentation",
    "pluralName": "hologramm-praesentations",
    "displayName": "Hologramm-Präsentation"
  },
  "options": {
    "draftAndPublish": true
  },
  "pluginOptions": {
    "i18n": {
      "localized": true
    }
  },
  "attributes": {
    "Title": {
      "pluginOptions": {
        "i18n": {
          "localized": true
        }
      },
      "type": "string",
      "required": true
    },
    "Beschreibung": {
      "pluginOptions": {
        "i18n": {
          "localized": true
        }
      },
      "type": "richtext",
      "required": true
    },
    "AbschnittHeadline": {
      "pluginOptions": {
        "i18n": {
          "localized": true
        }
      },
      "type": "string"
    },
    "AbschnittText": {
      "pluginOptions": {
        "i18n": {
          "localized": true
        }
      },
      "type": "richtext",
      "required": true
    },
    "youtubeVideos": {
      "allowedTypes": [
        "images",
        "files",
        "videos",
        "audios"
      ],
      "type": "media",
      "multiple": true,
      "pluginOptions": {
        "i18n": {
          "localized": true
        }
      }
    },
    "HeroImage": {
      "allowedTypes": [
        "images",
        "files",
        "videos",
        "audios"
      ],
      "type": "media",
      "multiple": false,
      "pluginOptions": {
        "i18n": {
          "localized": true
        }
      }
    },
    "Images": {
      "allowedTypes": [
        "images",
        "files",
        "videos",
        "audios"
      ],
      "type": "media",
      "multiple": true,
      "pluginOptions": {
        "i18n": {
          "localized": true
        }
      }
    },
    "youtubeTitleSection": {
      "pluginOptions": {
        "i18n": {
          "localized": true
        }
      },
      "type": "string"
    }
  }
}
